object_tool/__init__.py
object_tool/admin.py
object_tool/apps.py
object_tool/shortcuts.py
object_tool/sites.py
object_tool/utils.py
object_tool/static/admin/css/object-tool.css
object_tool/template/__init__.py
object_tool/template/loaders.py
object_tool/templates/admin/object_tool/baseview.html
object_tool/templates/admin/object_tool/breadcrumbs.html
object_tool/templates/admin/object_tool/form.html
object_tool/templates/admin/object_tool/object-tools-items.html
object_tool/tests/__init__.py
object_tool/tests/base.py
object_tool/tests/settings.py
object_tool/tests/test_admin.py
object_tool/tests/test_compatibilities.py
object_tool/tests/test_shortcuts.py
object_tool/tests/test_sites.py
object_tool/tests/urls.py
django_object_tool-0.0.12.dist-info/LICENSE
django_object_tool-0.0.12.dist-info/METADATA
django_object_tool-0.0.12.dist-info/WHEEL
django_object_tool-0.0.12.dist-info/top_level.txt
django_object_tool-0.0.12.dist-info/RECORD
